pytreemap.py
template.py
pytm_cli-0.0.2.dist-info/DESCRIPTION.rst
pytm_cli-0.0.2.dist-info/METADATA
pytm_cli-0.0.2.dist-info/RECORD
pytm_cli-0.0.2.dist-info/WHEEL
pytm_cli-0.0.2.dist-info/entry_points.txt
pytm_cli-0.0.2.dist-info/metadata.json
pytm_cli-0.0.2.dist-info/top_level.txt
