Metadata-Version: 2.0
Name: pytm-cli
Version: 0.0.2
Summary: 树图渲染命令行工具-利用 JSON 数据生成 HTML 格式的树图
Home-page: https://github.com/chenjiandongx/pytm-cli
Author: UNKNOWN
Author-email: chenjiandongx@qq.com
License: MIT
Platform: UNKNOWN
Requires-Dist: jinja2
